jgtcore/__init__.py
jgtcore/compatibility.py
jgtcore/constants.py
jgtcore/core.py
jgtcore/example.py
jgtcore/test_core.py
jgtcore/timeframe.py
jgtcore/cli/__init__.py
jgtcore/cli/common.py
jgtcore/cli/helper.py
jgtcore/env/__init__.py
jgtcore/env/loaders.py
jgtcore/fx/__init__.py
jgtcore/fx/transact.py
jgtcore/logging/__init__.py
jgtcore/logging/jgtlogging.py
jgtcore/os/__init__.py
jgtcore/os/helpers.py
jgtcore-0.2.5.dist-info/licenses/LICENSE
jgtcore-0.2.5.dist-info/METADATA
jgtcore-0.2.5.dist-info/WHEEL
jgtcore-0.2.5.dist-info/top_level.txt
jgtcore-0.2.5.dist-info/RECORD
