Metadata-Version: 2.4
Name: jgtcore
Version: 0.2.5
Summary: Comprehensive core library for JGT applications - migrated from jgtutils with full compatibility
Author-email: Guillaume Isabelle <jgi@jgwill.com>
License-Expression: MIT
Project-URL: Homepage, https://github.com/jgwill/jgtcore
Project-URL: Bug Tracker, https://github.com/jgwill/jgtcore/issues
Project-URL: Documentation, https://github.com/jgwill/jgtcore#readme
Project-URL: Source Code, https://github.com/jgwill/jgtcore
Keywords: configuration,settings,utilities,jgt,trading,fx,cli,logging
Classifier: Development Status :: 4 - Beta
Classifier: Intended Audience :: Developers
Classifier: Programming Language :: Python :: 3
Classifier: Programming Language :: Python :: 3.7
Classifier: Programming Language :: Python :: 3.8
Classifier: Programming Language :: Python :: 3.9
Classifier: Programming Language :: Python :: 3.10
Classifier: Programming Language :: Python :: 3.11
Requires-Python: >=3.7
License-File: LICENSE
Requires-Dist: python-dotenv
Requires-Dist: ruamel.yaml>=0.18.6
Provides-Extra: dev
Requires-Dist: pytest; extra == "dev"
Requires-Dist: pytest-cov; extra == "dev"
Requires-Dist: coverage; extra == "dev"
Requires-Dist: black; extra == "dev"
Requires-Dist: isort; extra == "dev"
Requires-Dist: flake8; extra == "dev"
Requires-Dist: build; extra == "dev"
Requires-Dist: twine; extra == "dev"
Dynamic: license-file
